glitter/__init__.py
glitter/__main__.py
glitter/app.py
glitter/cli.py
glitter/config.py
glitter/discovery.py
glitter/history.py
glitter/language.py
glitter/security.py
glitter/transfer.py
glitter/trust.py
glitter/ui.py
glitter/utils.py
glitter_cli-0.6.12.dist-info/METADATA
glitter_cli-0.6.12.dist-info/WHEEL
glitter_cli-0.6.12.dist-info/entry_points.txt
glitter_cli-0.6.12.dist-info/licenses/LICENSE
glitter_cli-0.6.12.dist-info/RECORD
