Metadata-Version: 2.4
Name: glitter-cli
Version: 0.6.12
Summary: Simple File Transfer CLI
Project-URL: Repository, https://github.com/scarletkc/glitter
Author: scarletkc
License: MIT
License-File: LICENSE
Keywords: cli,file-transfer,glitter,lan
Classifier: Development Status :: 4 - Beta
Classifier: Environment :: Console
Classifier: Intended Audience :: End Users/Desktop
Classifier: License :: OSI Approved :: MIT License
Classifier: Operating System :: OS Independent
Classifier: Programming Language :: Python
Classifier: Programming Language :: Python :: 3
Classifier: Topic :: Communications :: File Sharing
Classifier: Topic :: System :: Networking
Requires-Python: >=3.9
Requires-Dist: cryptography>=46.0.3
Requires-Dist: rich>=14.2.0
